<annotation>
	<folder>m</folder>
	<filename>trayyyy4 (177).jpg</filename>
	<path>C:\Users\Ikke\Desktop\m\trayyyy4 (177).jpg</path>
	<source>
		<database>Unknown</database>
	</source>
	<size>
		<width>1062</width>
		<height>598</height>
		<depth>3</depth>
	</size>
	<segmented>0</segmented>
	<object>
		<name>tray</name>
		<pose>Unspecified</pose>
		<truncated>0</truncated>
		<difficult>0</difficult>
		<bndbox>
			<xmin>515</xmin>
			<ymin>135</ymin>
			<xmax>584</xmax>
			<ymax>190</ymax>
		</bndbox>
	</object>
	<object>
		<name>tray</name>
		<pose>Unspecified</pose>
		<truncated>0</truncated>
		<difficult>0</difficult>
		<bndbox>
			<xmin>832</xmin>
			<ymin>74</ymin>
			<xmax>938</xmax>
			<ymax>121</ymax>
		</bndbox>
	</object>
</annotation>
